unichat/__init__.py
unichat/models.py
unichat/unified_chat_api.py
llm_unichat-0.1.2.dist-info/LICENSE
llm_unichat-0.1.2.dist-info/METADATA
llm_unichat-0.1.2.dist-info/WHEEL
llm_unichat-0.1.2.dist-info/top_level.txt
llm_unichat-0.1.2.dist-info/RECORD
