Metadata-Version: 2.1
Name: llm_unichat
Version: 0.1.2
Summary: Universal Python API client for OpenAI, MistralAI, Anthropic, xAI, and Google AI.
Home-page: https://github.com/amidabuddha/llm-unichat
Author: amidabuddha
Author-email: your.email@example.com
Classifier: Programming Language :: Python :: 3
Classifier: License :: OSI Approved :: MIT License
Classifier: Operating System :: OS Independent
Requires-Python: >=3.6
License-File: LICENSE
Requires-Dist: anthropic~=0.39.0
Requires-Dist: mistralai~=1.2.3
Requires-Dist: openai~=1.55.0
Requires-Dist: google-generativeai~=0.8.3
